{
  "openapi": "3.0.1",
  "info": {
    "title": "PCM API",
    "version": "v1"
  },
  "paths": {
    "/api/Auth/register": {
      "post": {
        "tags": [
          "Auth"
        ],
        "requestBody": {
          "content": {
            "application/json": {
              "schema": {
                "$ref": "#/components/schemas/RegisterModel"
              }
            },
            "text/json": {
              "schema": {
                "$ref": "#/components/schemas/RegisterModel"
              }
            },
            "application/*+json": {
              "schema": {
                "$ref": "#/components/schemas/RegisterModel"
              }
            }
          }
        },
        "responses": {
          "200": {
            "description": "Success"
          }
        }
      }
    },
    "/api/Auth/login": {
      "post": {
        "tags": [
          "Auth"
        ],
        "requestBody": {
          "content": {
            "application/json": {
              "schema": {
                "$ref": "#/components/schemas/LoginModel"
              }
            },
            "text/json": {
              "schema": {
                "$ref": "#/components/schemas/LoginModel"
              }
            },
            "application/*+json": {
              "schema": {
                "$ref": "#/components/schemas/LoginModel"
              }
            }
          }
        },
        "responses": {
          "200": {
            "description": "Success"
          }
        }
      }
    },
    "/api/Bookings": {
      "get": {
        "tags": [
          "Bookings"
        ],
        "responses": {
          "200": {
            "description": "Success",
            "content": {
              "text/plain": {
                "schema": {
                  "type": "array",
                  "items": { }
                }
              },
              "application/json": {
                "schema": {
                  "type": "array",
                  "items": { }
                }
              },
              "text/json": {
                "schema": {
                  "type": "array",
                  "items": { }
                }
              }
            }
          }
        }
      },
      "post": {
        "tags": [
          "Bookings"
        ],
        "requestBody": {
          "content": {
            "application/json": {
              "schema": {
                "$ref": "#/components/schemas/Booking"
              }
            },
            "text/json": {
              "schema": {
                "$ref": "#/components/schemas/Booking"
              }
            },
            "application/*+json": {
              "schema": {
                "$ref": "#/components/schemas/Booking"
              }
            }
          }
        },
        "responses": {
          "200": {
            "description": "Success"
          }
        }
      }
    },
    "/api/Bookings/{id}": {
      "get": {
        "tags": [
          "Bookings"
        ],
        "parameters": [
          {
            "name": "id",
            "in": "path",
            "required": true,
            "schema": {
              "type": "integer",
              "format": "int32"
            }
          }
        ],
        "responses": {
          "200": {
            "description": "Success"
          }
        }
      },
      "delete": {
        "tags": [
          "Bookings"
        ],
        "parameters": [
          {
            "name": "id",
            "in": "path",
            "required": true,
            "schema": {
              "type": "integer",
              "format": "int32"
            }
          }
        ],
        "responses": {
          "200": {
            "description": "Success"
          }
        }
      }
    },
    "/api/Bookings/stats": {
      "get": {
        "tags": [
          "Bookings"
        ],
        "responses": {
          "200": {
            "description": "Success"
          }
        }
      }
    },
    "/api/Challenges": {
      "get": {
        "tags": [
          "Challenges"
        ],
        "responses": {
          "200": {
            "description": "Success"
          }
        }
      },
      "post": {
        "tags": [
          "Challenges"
        ],
        "requestBody": {
          "content": {
            "application/json": {
              "schema": {
                "$ref": "#/components/schemas/Challenge"
              }
            },
            "text/json": {
              "schema": {
                "$ref": "#/components/schemas/Challenge"
              }
            },
            "application/*+json": {
              "schema": {
                "$ref": "#/components/schemas/Challenge"
              }
            }
          }
        },
        "responses": {
          "200": {
            "description": "Success"
          }
        }
      }
    },
    "/api/Challenges/{id}": {
      "delete": {
        "tags": [
          "Challenges"
        ],
        "parameters": [
          {
            "name": "id",
            "in": "path",
            "required": true,
            "schema": {
              "type": "integer",
              "format": "int32"
            }
          }
        ],
        "responses": {
          "200": {
            "description": "Success"
          }
        }
      }
    },
    "/api/Courts": {
      "get": {
        "tags": [
          "Courts"
        ],
        "responses": {
          "200": {
            "description": "Success"
          }
        }
      },
      "post": {
        "tags": [
          "Courts"
        ],
        "requestBody": {
          "content": {
            "application/json": {
              "schema": {
                "$ref": "#/components/schemas/Court"
              }
            },
            "text/json": {
              "schema": {
                "$ref": "#/components/schemas/Court"
              }
            },
            "application/*+json": {
              "schema": {
                "$ref": "#/components/schemas/Court"
              }
            }
          }
        },
        "responses": {
          "200": {
            "description": "Success"
          }
        }
      }
    },
    "/api/Courts/{id}": {
      "get": {
        "tags": [
          "Courts"
        ],
        "parameters": [
          {
            "name": "id",
            "in": "path",
            "required": true,
            "schema": {
              "type": "integer",
              "format": "int32"
            }
          }
        ],
        "responses": {
          "200": {
            "description": "Success"
          }
        }
      },
      "put": {
        "tags": [
          "Courts"
        ],
        "parameters": [
          {
            "name": "id",
            "in": "path",
            "required": true,
            "schema": {
              "type": "integer",
              "format": "int32"
            }
          }
        ],
        "requestBody": {
          "content": {
            "application/json": {
              "schema": {
                "$ref": "#/components/schemas/Court"
              }
            },
            "text/json": {
              "schema": {
                "$ref": "#/components/schemas/Court"
              }
            },
            "application/*+json": {
              "schema": {
                "$ref": "#/components/schemas/Court"
              }
            }
          }
        },
        "responses": {
          "200": {
            "description": "Success"
          }
        }
      },
      "delete": {
        "tags": [
          "Courts"
        ],
        "parameters": [
          {
            "name": "id",
            "in": "path",
            "required": true,
            "schema": {
              "type": "integer",
              "format": "int32"
            }
          }
        ],
        "responses": {
          "200": {
            "description": "Success"
          }
        }
      }
    },
    "/api/Matches": {
      "get": {
        "tags": [
          "Matches"
        ],
        "responses": {
          "200": {
            "description": "Success"
          }
        }
      },
      "post": {
        "tags": [
          "Matches"
        ],
        "requestBody": {
          "content": {
            "application/json": {
              "schema": {
                "$ref": "#/components/schemas/Match"
              }
            },
            "text/json": {
              "schema": {
                "$ref": "#/components/schemas/Match"
              }
            },
            "application/*+json": {
              "schema": {
                "$ref": "#/components/schemas/Match"
              }
            }
          }
        },
        "responses": {
          "200": {
            "description": "Success"
          }
        }
      }
    },
    "/api/Members": {
      "get": {
        "tags": [
          "Members"
        ],
        "responses": {
          "200": {
            "description": "Success",
            "content": {
              "text/plain": {
                "schema": {
                  "type": "array",
                  "items": {
                    "$ref": "#/components/schemas/Member"
                  }
                }
              },
              "application/json": {
                "schema": {
                  "type": "array",
                  "items": {
                    "$ref": "#/components/schemas/Member"
                  }
                }
              },
              "text/json": {
                "schema": {
                  "type": "array",
                  "items": {
                    "$ref": "#/components/schemas/Member"
                  }
                }
              }
            }
          }
        }
      },
      "post": {
        "tags": [
          "Members"
        ],
        "requestBody": {
          "content": {
            "application/json": {
              "schema": {
                "$ref": "#/components/schemas/Member"
              }
            },
            "text/json": {
              "schema": {
                "$ref": "#/components/schemas/Member"
              }
            },
            "application/*+json": {
              "schema": {
                "$ref": "#/components/schemas/Member"
              }
            }
          }
        },
        "responses": {
          "200": {
            "description": "Success",
            "content": {
              "text/plain": {
                "schema": {
                  "$ref": "#/components/schemas/Member"
                }
              },
              "application/json": {
                "schema": {
                  "$ref": "#/components/schemas/Member"
                }
              },
              "text/json": {
                "schema": {
                  "$ref": "#/components/schemas/Member"
                }
              }
            }
          }
        }
      }
    },
    "/api/Members/{id}": {
      "get": {
        "tags": [
          "Members"
        ],
        "parameters": [
          {
            "name": "id",
            "in": "path",
            "required": true,
            "schema": {
              "type": "integer",
              "format": "int32"
            }
          }
        ],
        "responses": {
          "200": {
            "description": "Success",
            "content": {
              "text/plain": {
                "schema": {
                  "$ref": "#/components/schemas/Member"
                }
              },
              "application/json": {
                "schema": {
                  "$ref": "#/components/schemas/Member"
                }
              },
              "text/json": {
                "schema": {
                  "$ref": "#/components/schemas/Member"
                }
              }
            }
          }
        }
      },
      "put": {
        "tags": [
          "Members"
        ],
        "parameters": [
          {
            "name": "id",
            "in": "path",
            "required": true,
            "schema": {
              "type": "integer",
              "format": "int32"
            }
          }
        ],
        "requestBody": {
          "content": {
            "application/json": {
              "schema": {
                "$ref": "#/components/schemas/Member"
              }
            },
            "text/json": {
              "schema": {
                "$ref": "#/components/schemas/Member"
              }
            },
            "application/*+json": {
              "schema": {
                "$ref": "#/components/schemas/Member"
              }
            }
          }
        },
        "responses": {
          "200": {
            "description": "Success"
          }
        }
      },
      "delete": {
        "tags": [
          "Members"
        ],
        "parameters": [
          {
            "name": "id",
            "in": "path",
            "required": true,
            "schema": {
              "type": "integer",
              "format": "int32"
            }
          }
        ],
        "responses": {
          "200": {
            "description": "Success"
          }
        }
      }
    },
    "/api/Participants": {
      "get": {
        "tags": [
          "Participants"
        ],
        "responses": {
          "200": {
            "description": "Success"
          }
        }
      },
      "post": {
        "tags": [
          "Participants"
        ],
        "requestBody": {
          "content": {
            "application/json": {
              "schema": {
                "$ref": "#/components/schemas/Participant"
              }
            },
            "text/json": {
              "schema": {
                "$ref": "#/components/schemas/Participant"
              }
            },
            "application/*+json": {
              "schema": {
                "$ref": "#/components/schemas/Participant"
              }
            }
          }
        },
        "responses": {
          "200": {
            "description": "Success"
          }
        }
      }
    },
    "/api/Products": {
      "get": {
        "tags": [
          "Products"
        ],
        "responses": {
          "200": {
            "description": "Success",
            "content": {
              "text/plain": {
                "schema": {
                  "type": "array",
                  "items": {
                    "$ref": "#/components/schemas/Product"
                  }
                }
              },
              "application/json": {
                "schema": {
                  "type": "array",
                  "items": {
                    "$ref": "#/components/schemas/Product"
                  }
                }
              },
              "text/json": {
                "schema": {
                  "type": "array",
                  "items": {
                    "$ref": "#/components/schemas/Product"
                  }
                }
              }
            }
          }
        }
      },
      "post": {
        "tags": [
          "Products"
        ],
        "requestBody": {
          "content": {
            "application/json": {
              "schema": {
                "$ref": "#/components/schemas/Product"
              }
            },
            "text/json": {
              "schema": {
                "$ref": "#/components/schemas/Product"
              }
            },
            "application/*+json": {
              "schema": {
                "$ref": "#/components/schemas/Product"
              }
            }
          }
        },
        "responses": {
          "200": {
            "description": "Success",
            "content": {
              "text/plain": {
                "schema": {
                  "$ref": "#/components/schemas/Product"
                }
              },
              "application/json": {
                "schema": {
                  "$ref": "#/components/schemas/Product"
                }
              },
              "text/json": {
                "schema": {
                  "$ref": "#/components/schemas/Product"
                }
              }
            }
          }
        }
      }
    },
    "/api/Products/{id}": {
      "get": {
        "tags": [
          "Products"
        ],
        "parameters": [
          {
            "name": "id",
            "in": "path",
            "required": true,
            "schema": {
              "type": "integer",
              "format": "int32"
            }
          }
        ],
        "responses": {
          "200": {
            "description": "Success",
            "content": {
              "text/plain": {
                "schema": {
                  "$ref": "#/components/schemas/Product"
                }
              },
              "application/json": {
                "schema": {
                  "$ref": "#/components/schemas/Product"
                }
              },
              "text/json": {
                "schema": {
                  "$ref": "#/components/schemas/Product"
                }
              }
            }
          }
        }
      },
      "put": {
        "tags": [
          "Products"
        ],
        "parameters": [
          {
            "name": "id",
            "in": "path",
            "required": true,
            "schema": {
              "type": "integer",
              "format": "int32"
            }
          }
        ],
        "requestBody": {
          "content": {
            "application/json": {
              "schema": {
                "$ref": "#/components/schemas/Product"
              }
            },
            "text/json": {
              "schema": {
                "$ref": "#/components/schemas/Product"
              }
            },
            "application/*+json": {
              "schema": {
                "$ref": "#/components/schemas/Product"
              }
            }
          }
        },
        "responses": {
          "200": {
            "description": "Success"
          }
        }
      },
      "delete": {
        "tags": [
          "Products"
        ],
        "parameters": [
          {
            "name": "id",
            "in": "path",
            "required": true,
            "schema": {
              "type": "integer",
              "format": "int32"
            }
          }
        ],
        "responses": {
          "200": {
            "description": "Success"
          }
        }
      }
    },
    "/api/TransactionCategories": {
      "get": {
        "tags": [
          "TransactionCategories"
        ],
        "responses": {
          "200": {
            "description": "Success",
            "content": {
              "text/plain": {
                "schema": {
                  "type": "array",
                  "items": {
                    "$ref": "#/components/schemas/TransactionCategory"
                  }
                }
              },
              "application/json": {
                "schema": {
                  "type": "array",
                  "items": {
                    "$ref": "#/components/schemas/TransactionCategory"
                  }
                }
              },
              "text/json": {
                "schema": {
                  "type": "array",
                  "items": {
                    "$ref": "#/components/schemas/TransactionCategory"
                  }
                }
              }
            }
          }
        }
      },
      "post": {
        "tags": [
          "TransactionCategories"
        ],
        "requestBody": {
          "content": {
            "application/json": {
              "schema": {
                "$ref": "#/components/schemas/TransactionCategory"
              }
            },
            "text/json": {
              "schema": {
                "$ref": "#/components/schemas/TransactionCategory"
              }
            },
            "application/*+json": {
              "schema": {
                "$ref": "#/components/schemas/TransactionCategory"
              }
            }
          }
        },
        "responses": {
          "200": {
            "description": "Success",
            "content": {
              "text/plain": {
                "schema": {
                  "$ref": "#/components/schemas/TransactionCategory"
                }
              },
              "application/json": {
                "schema": {
                  "$ref": "#/components/schemas/TransactionCategory"
                }
              },
              "text/json": {
                "schema": {
                  "$ref": "#/components/schemas/TransactionCategory"
                }
              }
            }
          }
        }
      }
    },
    "/api/TransactionCategories/{id}": {
      "get": {
        "tags": [
          "TransactionCategories"
        ],
        "parameters": [
          {
            "name": "id",
            "in": "path",
            "required": true,
            "schema": {
              "type": "integer",
              "format": "int32"
            }
          }
        ],
        "responses": {
          "200": {
            "description": "Success",
            "content": {
              "text/plain": {
                "schema": {
                  "$ref": "#/components/schemas/TransactionCategory"
                }
              },
              "application/json": {
                "schema": {
                  "$ref": "#/components/schemas/TransactionCategory"
                }
              },
              "text/json": {
                "schema": {
                  "$ref": "#/components/schemas/TransactionCategory"
                }
              }
            }
          }
        }
      },
      "put": {
        "tags": [
          "TransactionCategories"
        ],
        "parameters": [
          {
            "name": "id",
            "in": "path",
            "required": true,
            "schema": {
              "type": "integer",
              "format": "int32"
            }
          }
        ],
        "requestBody": {
          "content": {
            "application/json": {
              "schema": {
                "$ref": "#/components/schemas/TransactionCategory"
              }
            },
            "text/json": {
              "schema": {
                "$ref": "#/components/schemas/TransactionCategory"
              }
            },
            "application/*+json": {
              "schema": {
                "$ref": "#/components/schemas/TransactionCategory"
              }
            }
          }
        },
        "responses": {
          "200": {
            "description": "Success"
          }
        }
      },
      "delete": {
        "tags": [
          "TransactionCategories"
        ],
        "parameters": [
          {
            "name": "id",
            "in": "path",
            "required": true,
            "schema": {
              "type": "integer",
              "format": "int32"
            }
          }
        ],
        "responses": {
          "200": {
            "description": "Success"
          }
        }
      }
    },
    "/api/Transactions": {
      "get": {
        "tags": [
          "Transactions"
        ],
        "responses": {
          "200": {
            "description": "Success",
            "content": {
              "text/plain": {
                "schema": {
                  "type": "array",
                  "items": {
                    "$ref": "#/components/schemas/Transaction"
                  }
                }
              },
              "application/json": {
                "schema": {
                  "type": "array",
                  "items": {
                    "$ref": "#/components/schemas/Transaction"
                  }
                }
              },
              "text/json": {
                "schema": {
                  "type": "array",
                  "items": {
                    "$ref": "#/components/schemas/Transaction"
                  }
                }
              }
            }
          }
        }
      },
      "post": {
        "tags": [
          "Transactions"
        ],
        "requestBody": {
          "content": {
            "application/json": {
              "schema": {
                "$ref": "#/components/schemas/Transaction"
              }
            },
            "text/json": {
              "schema": {
                "$ref": "#/components/schemas/Transaction"
              }
            },
            "application/*+json": {
              "schema": {
                "$ref": "#/components/schemas/Transaction"
              }
            }
          }
        },
        "responses": {
          "200": {
            "description": "Success",
            "content": {
              "text/plain": {
                "schema": {
                  "$ref": "#/components/schemas/Transaction"
                }
              },
              "application/json": {
                "schema": {
                  "$ref": "#/components/schemas/Transaction"
                }
              },
              "text/json": {
                "schema": {
                  "$ref": "#/components/schemas/Transaction"
                }
              }
            }
          }
        }
      }
    },
    "/api/Transactions/{id}": {
      "get": {
        "tags": [
          "Transactions"
        ],
        "parameters": [
          {
            "name": "id",
            "in": "path",
            "required": true,
            "schema": {
              "type": "integer",
              "format": "int32"
            }
          }
        ],
        "responses": {
          "200": {
            "description": "Success",
            "content": {
              "text/plain": {
                "schema": {
                  "$ref": "#/components/schemas/Transaction"
                }
              },
              "application/json": {
                "schema": {
                  "$ref": "#/components/schemas/Transaction"
                }
              },
              "text/json": {
                "schema": {
                  "$ref": "#/components/schemas/Transaction"
                }
              }
            }
          }
        }
      },
      "put": {
        "tags": [
          "Transactions"
        ],
        "parameters": [
          {
            "name": "id",
            "in": "path",
            "required": true,
            "schema": {
              "type": "integer",
              "format": "int32"
            }
          }
        ],
        "requestBody": {
          "content": {
            "application/json": {
              "schema": {
                "$ref": "#/components/schemas/Transaction"
              }
            },
            "text/json": {
              "schema": {
                "$ref": "#/components/schemas/Transaction"
              }
            },
            "application/*+json": {
              "schema": {
                "$ref": "#/components/schemas/Transaction"
              }
            }
          }
        },
        "responses": {
          "200": {
            "description": "Success"
          }
        }
      },
      "delete": {
        "tags": [
          "Transactions"
        ],
        "parameters": [
          {
            "name": "id",
            "in": "path",
            "required": true,
            "schema": {
              "type": "integer",
              "format": "int32"
            }
          }
        ],
        "responses": {
          "200": {
            "description": "Success"
          }
        }
      }
    },
    "/api/Transactions/total": {
      "get": {
        "tags": [
          "Transactions"
        ],
        "responses": {
          "200": {
            "description": "Success"
          }
        }
      }
    },
    "/api/Transactions/by-category": {
      "get": {
        "tags": [
          "Transactions"
        ],
        "responses": {
          "200": {
            "description": "Success"
          }
        }
      }
    },
    "/api/Transactions/by-date": {
      "get": {
        "tags": [
          "Transactions"
        ],
        "parameters": [
          {
            "name": "from",
            "in": "query",
            "schema": {
              "type": "string",
              "format": "date-time"
            }
          },
          {
            "name": "to",
            "in": "query",
            "schema": {
              "type": "string",
              "format": "date-time"
            }
          }
        ],
        "responses": {
          "200": {
            "description": "Success"
          }
        }
      }
    },
    "/api/Transactions/summary": {
      "get": {
        "tags": [
          "Transactions"
        ],
        "responses": {
          "200": {
            "description": "Success"
          }
        }
      }
    },
    "/api/Transactions/by-date-range": {
      "get": {
        "tags": [
          "Transactions"
        ],
        "parameters": [
          {
            "name": "from",
            "in": "query",
            "schema": {
              "type": "string",
              "format": "date-time"
            }
          },
          {
            "name": "to",
            "in": "query",
            "schema": {
              "type": "string",
              "format": "date-time"
            }
          }
        ],
        "responses": {
          "200": {
            "description": "Success"
          }
        }
      }
    },
    "/api/Transactions/by-category/{categoryId}": {
      "get": {
        "tags": [
          "Transactions"
        ],
        "parameters": [
          {
            "name": "categoryId",
            "in": "path",
            "required": true,
            "schema": {
              "type": "integer",
              "format": "int32"
            }
          }
        ],
        "responses": {
          "200": {
            "description": "Success"
          }
        }
      }
    },
    "/api/Transactions/report-by-category": {
      "get": {
        "tags": [
          "Transactions"
        ],
        "responses": {
          "200": {
            "description": "Success"
          }
        }
      }
    },
    "/api/Transactions/report-by-month": {
      "get": {
        "tags": [
          "Transactions"
        ],
        "parameters": [
          {
            "name": "year",
            "in": "query",
            "schema": {
              "type": "integer",
              "format": "int32"
            }
          }
        ],
        "responses": {
          "200": {
            "description": "Success"
          }
        }
      }
    },
    "/WeatherForecast": {
      "get": {
        "tags": [
          "WeatherForecast"
        ],
        "operationId": "GetWeatherForecast",
        "responses": {
          "200": {
            "description": "Success",
            "content": {
              "text/plain": {
                "schema": {
                  "type": "array",
                  "items": {
                    "$ref": "#/components/schemas/WeatherForecast"
                  }
                }
              },
              "application/json": {
                "schema": {
                  "type": "array",
                  "items": {
                    "$ref": "#/components/schemas/WeatherForecast"
                  }
                }
              },
              "text/json": {
                "schema": {
                  "type": "array",
                  "items": {
                    "$ref": "#/components/schemas/WeatherForecast"
                  }
                }
              }
            }
          }
        }
      }
    }
  },
  "components": {
    "schemas": {
      "Booking": {
        "required": [
          "endTime",
          "startTime"
        ],
        "type": "object",
        "properties": {
          "id": {
            "type": "integer",
            "format": "int32"
          },
          "startTime": {
            "type": "string",
            "format": "date-time"
          },
          "endTime": {
            "type": "string",
            "format": "date-time"
          },
          "courtId": {
            "type": "integer",
            "format": "int32"
          },
          "court": {
            "$ref": "#/components/schemas/Court"
          },
          "memberId": {
            "type": "integer",
            "format": "int32"
          },
          "member": {
            "$ref": "#/components/schemas/Member"
          }
        },
        "additionalProperties": false
      },
      "Challenge": {
        "required": [
          "name"
        ],
        "type": "object",
        "properties": {
          "id": {
            "type": "integer",
            "format": "int32"
          },
          "name": {
            "minLength": 1,
            "type": "string"
          },
          "participants": {
            "type": "array",
            "items": {
              "$ref": "#/components/schemas/Participant"
            },
            "nullable": true
          },
          "matches": {
            "type": "array",
            "items": {
              "$ref": "#/components/schemas/Match"
            },
            "nullable": true
          }
        },
        "additionalProperties": false
      },
      "Court": {
        "required": [
          "name"
        ],
        "type": "object",
        "properties": {
          "id": {
            "type": "integer",
            "format": "int32"
          },
          "name": {
            "maxLength": 100,
            "minLength": 1,
            "type": "string"
          },
          "bookings": {
            "type": "array",
            "items": {
              "$ref": "#/components/schemas/Booking"
            },
            "nullable": true
          }
        },
        "additionalProperties": false
      },
      "LoginModel": {
        "type": "object",
        "properties": {
          "email": {
            "type": "string",
            "nullable": true
          },
          "password": {
            "type": "string",
            "nullable": true
          }
        },
        "additionalProperties": false
      },
      "Match": {
        "type": "object",
        "properties": {
          "id": {
            "type": "integer",
            "format": "int32"
          },
          "matchDate": {
            "type": "string",
            "format": "date-time"
          },
          "team1_Player1Id": {
            "type": "integer",
            "format": "int32"
          },
          "team1_Player2Id": {
            "type": "integer",
            "format": "int32"
          },
          "team2_Player1Id": {
            "type": "integer",
            "format": "int32"
          },
          "team2_Player2Id": {
            "type": "integer",
            "format": "int32"
          },
          "challengeId": {
            "type": "integer",
            "format": "int32",
            "nullable": true
          },
          "challenge": {
            "$ref": "#/components/schemas/Challenge"
          }
        },
        "additionalProperties": false
      },
      "Member": {
        "required": [
          "name"
        ],
        "type": "object",
        "properties": {
          "id": {
            "type": "integer",
            "format": "int32"
          },
          "name": {
            "maxLength": 100,
            "minLength": 1,
            "type": "string"
          },
          "transactions": {
            "type": "array",
            "items": {
              "$ref": "#/components/schemas/Transaction"
            },
            "nullable": true
          },
          "bookings": {
            "type": "array",
            "items": {
              "$ref": "#/components/schemas/Booking"
            },
            "nullable": true
          }
        },
        "additionalProperties": false
      },
      "Participant": {
        "type": "object",
        "properties": {
          "id": {
            "type": "integer",
            "format": "int32"
          },
          "memberId": {
            "type": "integer",
            "format": "int32"
          },
          "member": {
            "$ref": "#/components/schemas/Member"
          },
          "challengeId": {
            "type": "integer",
            "format": "int32"
          },
          "challenge": {
            "$ref": "#/components/schemas/Challenge"
          }
        },
        "additionalProperties": false
      },
      "Product": {
        "required": [
          "name"
        ],
        "type": "object",
        "properties": {
          "id": {
            "type": "integer",
            "format": "int32"
          },
          "name": {
            "maxLength": 100,
            "minLength": 1,
            "type": "string"
          },
          "price": {
            "maximum": 999999999,
            "minimum": 0,
            "type": "number",
            "format": "double"
          },
          "description": {
            "maxLength": 500,
            "type": "string",
            "nullable": true
          }
        },
        "additionalProperties": false
      },
      "RegisterModel": {
        "type": "object",
        "properties": {
          "email": {
            "type": "string",
            "nullable": true
          },
          "password": {
            "type": "string",
            "nullable": true
          }
        },
        "additionalProperties": false
      },
      "Transaction": {
        "required": [
          "name"
        ],
        "type": "object",
        "properties": {
          "id": {
            "type": "integer",
            "format": "int32"
          },
          "name": {
            "maxLength": 100,
            "minLength": 1,
            "type": "string"
          },
          "amount": {
            "type": "number",
            "format": "double"
          },
          "date": {
            "type": "string",
            "format": "date-time"
          },
          "note": {
            "type": "string",
            "nullable": true
          },
          "memberId": {
            "type": "integer",
            "format": "int32"
          },
          "member": {
            "$ref": "#/components/schemas/Member"
          },
          "transactionCategoryId": {
            "type": "integer",
            "format": "int32"
          },
          "category": {
            "$ref": "#/components/schemas/TransactionCategory"
          }
        },
        "additionalProperties": false
      },
      "TransactionCategory": {
        "required": [
          "name"
        ],
        "type": "object",
        "properties": {
          "id": {
            "type": "integer",
            "format": "int32"
          },
          "name": {
            "maxLength": 100,
            "minLength": 1,
            "type": "string"
          },
          "transactions": {
            "type": "array",
            "items": {
              "$ref": "#/components/schemas/Transaction"
            },
            "nullable": true
          }
        },
        "additionalProperties": false
      },
      "WeatherForecast": {
        "type": "object",
        "properties": {
          "date": {
            "type": "string",
            "format": "date"
          },
          "temperatureC": {
            "type": "integer",
            "format": "int32"
          },
          "temperatureF": {
            "type": "integer",
            "format": "int32",
            "readOnly": true
          },
          "summary": {
            "type": "string",
            "nullable": true
          }
        },
        "additionalProperties": false
      }
    },
    "securitySchemes": {
      "Bearer": {
        "type": "http",
        "description": "Enter: Bearer {your JWT token}",
        "scheme": "bearer",
        "bearerFormat": "JWT"
      }
    }
  },
  "security": [
    {
      "Bearer": [ ]
    }
  ]
}